deflow/__about__.py
deflow/__init__.py
deflow/__main__.py
deflow/__types.py
deflow/conf.py
deflow/errors.py
deflow/flow.py
deflow/assets/__init__.py
deflow/assets/models.py
deflow/assets/utils.py
deflow/assets/v1/__init__.py
deflow/assets/v1/core/__init__.py
deflow/assets/v1/core/__types.py
deflow/assets/v1/core/errors.py
deflow/assets/v1/core/models.py
deflow/assets/v1/core/tasks.py
deflow/assets/v1/core/utils.py
deflow/assets/v1/templates/backfill.yml
deflow/assets/v1/templates/group.yml
deflow/assets/v1/templates/process.yml
deflow/assets/v1/templates/stream.yml
deflow/assets/v2/__init__.py
deflow/assets/v2/core/__init__.py
deflow/assets/v2/core/errors.py
deflow/assets/v2/core/models.py
deflow/assets/v2/core/tasks.py
deflow/assets/v2/core/utils.py
deflow/assets/v2/templates/backfill.yml
deflow/assets/v2/templates/node.yml
deflow/assets/v2/templates/pipeline.yml
deflow/assets/v3/__init__.py
deflow/assets/v3/core/__init__.py
deflow/assets/v3/core/errors.py
deflow/assets/v3/core/models.py
deflow/assets/v3/core/utils.py
deflow-0.0.6.dist-info/METADATA
deflow-0.0.6.dist-info/WHEEL
deflow-0.0.6.dist-info/entry_points.txt
deflow-0.0.6.dist-info/licenses/LICENSE
deflow-0.0.6.dist-info/RECORD
