Metadata-Version: 2.4
Name: deflow
Version: 0.0.6
Summary: Lightweight Declarative Data Framework
Project-URL: Homepage, https://github.com/ddeutils/deflow/
Project-URL: Source Code, https://github.com/ddeutils/deflow/
Author-email: ddeutils <korawich.anu@gmail.com>
License-Expression: MIT
License-File: LICENSE
Keywords: declarative,framework
Classifier: Development Status :: 4 - Beta
Classifier: Intended Audience :: Developers
Classifier: Natural Language :: English
Classifier: Operating System :: OS Independent
Classifier: Programming Language :: Python
Classifier: Programming Language :: Python :: 3 :: Only
Classifier: Programming Language :: Python :: 3.9
Classifier: Programming Language :: Python :: 3.10
Classifier: Programming Language :: Python :: 3.11
Classifier: Programming Language :: Python :: 3.12
Classifier: Programming Language :: Python :: 3.13
Classifier: Topic :: Utilities
Requires-Python: >=3.9.13
Requires-Dist: ddeutil-io>=0.2.16
Requires-Dist: ddeutil-workflow==0.0.85
Requires-Dist: python-dotenv==1.1.1
Requires-Dist: typer<1.0.0,>=0.16.0
